citation_extractor/__init__.py
citation_extractor/base_settings.py
citation_extractor/core.py
citation_extractor/crfpp_wrap.py
citation_extractor/eval.py
citation_extractor/pipeline.py
citation_extractor/preproc.py
citation_extractor/process.py
citation_extractor/relex.py
citation_extractor/settings.py
citation_extractor/Tests/__init__.py
citation_extractor/Tests/test_FeatureExtractor.py
citation_extractor/Tests/test_IO.py
citation_extractor/Tests/test_jstor.py
citation_extractor/Tests/test_xmlrpc_client.py
citation_extractor/Tests/test_xmlrpc_server.py
citation_extractor/Utils/FastDict.py
citation_extractor/Utils/IO.py
citation_extractor/Utils/__init__.py
citation_extractor/Utils/actlearn.py
citation_extractor/Utils/aph_corpus.py
citation_extractor/Utils/clients.py
citation_extractor/Utils/conll02tostandoff.py
citation_extractor/Utils/jstor.py
citation_extractor/Utils/networks.py
citation_extractor/Utils/sentencesplit.py
citation_extractor/Utils/services.py
citation_extractor/Utils/ssplit.py
citation_extractor/Utils/sspostproc.py
citation_extractor/Utils/strmatching.py
citation_extractor/crfpp_templates/baseline.tpl
citation_extractor/crfpp_templates/crex.tpl
citation_extractor/crfpp_templates/template_1.tpl
citation_extractor/crfpp_templates/template_2.tpl
citation_extractor/crfpp_templates/template_3.tpl
citation_extractor/crfpp_templates/template_4.tpl
citation_extractor/crfpp_templates/template_5.tpl
citation_extractor/crfpp_templates/template_6.tpl
citation_extractor/data/10.2307_40236128
citation_extractor/data/10.2307_40236128.tagged
citation_extractor/data/10.2307_40236128.xml
citation_extractor/data/IOB_CRF_template.txt
citation_extractor/data/authors.csv
citation_extractor/data/crex.tpl
citation_extractor/data/output.html
citation_extractor/data/reply2html.xsl
citation_extractor/data/test.txt
citation_extractor/data/tests.txt
citation_extractor/data/works.csv
citation_extractor-1.6.3.dist-info/DESCRIPTION.rst
citation_extractor-1.6.3.dist-info/METADATA
citation_extractor-1.6.3.dist-info/RECORD
citation_extractor-1.6.3.dist-info/WHEEL
citation_extractor-1.6.3.dist-info/dependency_links.txt
citation_extractor-1.6.3.dist-info/metadata.json
citation_extractor-1.6.3.dist-info/top_level.txt
