Metadata-Version: 2.0
Name: citation-extractor
Version: 1.6.3
Summary: UNKNOWN
Home-page: http://github.com/mromanello/CitationExtractor/
Author: Matteo Romanello
Author-email: matteo.romanello@gmail.com
License: UNKNOWN
Platform: UNKNOWN
Requires-Dist: hucitlib
Requires-Dist: langid
Requires-Dist: docopt
Requires-Dist: pandas
Requires-Dist: scipy
Requires-Dist: treetagger
Requires-Dist: citation-parser (>=0.4.1)
Requires-Dist: sklearn-crfsuite
Requires-Dist: jellyfish (>=0.5.6)
Requires-Dist: stop-words (>=2015.2.23.1)
Requires-Dist: scikit-learn (>=0.16.1)
